hw3/mac.v
module mac (clk, reset_n, instruction, multiplier,
            multiplicand, stall, protect, result);
input clk;
input reset_n;
input [2:0] instruction;
input [15:0] multiplier;
input [15:0] multiplicand;
input stall;
output reg [7:0] protect;
output reg [31:0] result;
reg [39:0]queue[2:0];
reg [15:0] Multiplier;
reg [15:0] Multiplicand;
reg [39:0] temp;
reg [39:0] temp2;
reg [1:0] notice;
reg[1:0] notice1;
reg [39:0]temp3;
/* 	for first part of class
reg [39:0] queue[1:0];//the output queue
reg [39:0] last_output;
reg [1:0] counter;
reg [1:0] counter2;
*/
integer i;//just for for loop

always@(posedge clk or negedge reset_n)
begin
    if (reset_n == 1'b0)
    begin
        protect[7:0] = 8'h0;
        result[31:0] = 32'h0;
        temp=0;
        queue[0]=0;
        queue[1]=0;
    end
    else
    begin
        // reset_n == 1'b1

        Multiplier = multiplier;	// new multiplier`
        Multiplicand = multiplicand;// new multiplicand

        if (instruction == 3'b000 || instruction == 3'b100)
        begin
            temp = 40'd0;
            result[31:0]=32'h0;
            protect[7:0]=8'h0;
        end
        else if (instruction == 3'b001)
        begin
            notice = 2'd0;
            if (Multiplier[15] == 1'b1)
            begin
                notice=notice+1;// ...
                Multiplier=-Multiplier;
            end

            if (Multiplicand[15] == 1'b1)
            begin
                notice=notice+1;// ...
                Multiplicand=-Multiplicand;
            end

            temp=Multiplier*Multiplicand;
            if (notice%2 == 1)
                temp=-temp;
        end

        else if (instruction == 3'b010)
        begin
            temp2 = temp;
            notice = 2'd0;
            if (Multiplier[15] == 1'b1)
            begin
                notice=notice+1;
                Multiplier=-Multiplier;
            end
            if (Multiplicand[15] == 1'b1)
            begin
                notice=notice+1;
                Multiplicand=-Multiplicand;
            end
            temp=Multiplicand*Multiplier;
            if (notice%2 == 1)
                temp=-temp;
            temp3=temp2+temp;
            temp=temp3;
            // current result is stored in temp
        end
        else if (instruction == 3'b011)
        begin
            // saturation16

            if (temp > 40'h007fffffff && temp[39] == 1'b0)
                temp[31:0] = 32'h7FFFFFFF;
            else if (temp < 40'hff80000000 && temp[39] == 1'b1)
                temp[31:0] = 32'h80000000;
            // current result is stored in temp

        end
        else if (instruction == 3'b101)
        begin
            temp = 40'd0;
            // temp: temporary multiplication result
            // temp2: temporary mac result
            notice = 2'd0;
            notice1=2'd0;
            if (Multiplier[15] == 1'b1)
            begin
                notice=notice+1;
                Multiplier[15:8]=~Multiplier[15:8]+1;
            end
            if (Multiplier[7] == 1'b1)
            begin
                notice1=notice1+1;
                Multiplier[7:0]=~Multiplier+1;
            end

            if (Multiplicand[15] == 1'b1)
            begin
                notice=notice+1;
                Multiplicand[15:8]=~Multiplicand[15:8]+1;
            end
            if (Multiplicand[7] == 1'b1)
            begin
                notice1=notice1+1;
                Multiplicand[7:0]=~Multiplicand[7:0]+1;
            end
            temp[19:0]=Multiplicand[7:0]*Multiplier[7:0];
            temp[39:20]=Multiplicand[15:8]*Multiplier[15:8];
            //{protect[3:0],result[15:0]}=Multiplicand[7:0]*Multiplier[7:0];
            //{protect[7:4],result[31:16]}=Multiplicand[15:8]*Multiplier[15:8];
            if (notice%2 == 1)
            begin
                temp[39:20]=-temp[39:20];
                //{protect[3:0],result[15:0]}=~{protect[3:0],result[15:0]}+1;
                //{protect[7:4],result[31:16]}=~{Multiplicand[15:8]*Multiplier[15:8]}+1;
            end
            if(notice1%2==1)
                temp[19:0]=-temp[19:0];
            //temp={protect[7:4],result[31:16],protect[3:0],result[15:0]};
            // current result is stored in temp
            // current result is stored in temp
            temp3=temp;
            temp={temp3[39:36],temp3[19:16],temp3[35:20],temp3[15:0]};
        end
        else if (instruction == 3'b110)
        begin
            temp2=temp;
            temp = 40'd0;
            notice = 2'd0;
            notice1=2'd0;
            if (Multiplier[15] == 1'b1)
            begin
                notice=notice+1;
                Multiplier[15:8]=~Multiplier[15:8]+1;
            end
            if (Multiplier[7] == 1'b1)
            begin
                notice1=notice1+1;
                Multiplier[7:0]=~Multiplier[7:0]+1;
            end

            if (Multiplicand[15] == 1'b1)
            begin
                notice=notice+1;
                Multiplicand[15:8]=~Multiplicand[15:8]+1;
            end
            if (Multiplicand[7] == 1'b1)
            begin
                notice1=notice1+1;
                Multiplicand[7:0]=~Multiplicand[7:0]+1;
            end

            temp[19:0]=Multiplicand[7:0]*Multiplier[7:0];
            temp[39:20]=Multiplicand[15:8]*Multiplier[15:8];
            if (notice%2 == 1)
            begin
                temp[39:20]=-temp[39:20];
                //{protect[7:4],result[31:16]}=temp2[39:20]+((~(Multiplicand[15:8]*Multiplier[15:8]))+1);
            end
            if(notice1%2==1)
                temp[19:0]=-temp[19:0];

            temp3=temp;
            temp2={temp2[39:36],temp2[31:16],temp2[35:32],temp2[15:0]};
            temp={temp2[39:20]+temp3[39:20],temp2[19:0]+temp3[19:0]};
            temp={temp[39:36],temp[19:16],temp[35:20],temp[15:0]};
            //temp={temp2[39:20]+temp[39:20],temp2[19:0]+temp[19:0]};

            //temp={protect[7:4],result[31:16],protect[3:0],result[15:0]};
            // current result is stored in temp
            // current result is stored in temp

        end
        else if (instruction == 3'b111)
        begin
            // saturation16
            if ({temp[39:36],temp[31:16]} > 20'h07fff && temp[39] == 1'b0)
                temp[31:16] = 16'h7FFF;
            else if ({temp[39:36],temp[31:16]} < 20'hf8000 && temp[39] == 1'b1)
                temp[31:16] = 16'h8000;
            //for(i=36;i<40;i=i+1)
            // temp[i]=temp[31];

            if ({temp[35:32],temp[15:0]} > 20'h07fff && temp[35] == 1'b0)
                temp[15:0] = 16'h7FFF;
            else if ({temp[35:32],temp[15:0]} < 20'hf8000 && temp[35] == 1'b1)
                temp[15:0] = 16'h8000;
            //for(i=32;i<36;i=i+1)
            //temp[i]=temp[15];

            // current result is stored in temp
        end

        if (stall == 1'b0)
        begin
            //{protect, result} = temp;
            {protect,result}=queue[0];
            queue[0]=queue[1];
            queue[1]=temp;
        end
        else
        begin
            temp=queue[1];


        end

    end
end
endmodule

hw3/testfixture.v
// +FHDR------------------------------------------------------------------------
// Copyright (c) 2002, Global UniChip Corporation (UniChip).
// UniChip's Proprietary/Confidential
//
// All rights reserved. No part of this design may be reproduced or stored
// in a retrieval system, or transmitted, in any form or by any means,
// electronic, mechanical, photocopying, recording, or otherwise,
// without prior written permission of the Global UniChip Corporation.
// Unauthorized reproduction, duplication, use, or disclosure of this
// design will be deemed as infringement.
// -----------------------------------------------------------------------------
// FILE   : $Id: dic_2003.v,v 1.1 2003/04/25 04:01:19 ip01_11a Exp $
// TYPE   : Verilog Module
// AUTHOR : Tian-Sheuan Chang
// -----------------------------------------------------------------------------
// KEYWORDS :
// -----------------------------------------------------------------------------
// PURPOSE :
// -----------------------------------------------------------------------------
// PARAMETERS
// PARAM_NAME RANGE : DESCRIPTION : DEFAULT
// N/A
// -----------------------------------------------------------------------------
// REUSE ISSUES
// Reset Strategy :  rst_n
// Clock Domains :   clk
// Critical Timing :
// Test Features :   N/A
// Asynchronous I/F :N/A
// Scan Methodology :MUX-based scan F.F.
// Instantiations :  N/A
// Other :           N/A
// -FHDR------------------------------------------------------------------------

`timescale 1ns/10ps
module mac_sim;
//define for simulator parameters
`define HPHASE 10
//`define FSDB 1
`define CYCLE (`HPHASE * 2)
`define DUMPFILE_NAME "mac.fsdb"
//define for instruction
parameter CLEAR =  3'b000;
parameter CLEAR2 = 3'b100;
parameter MUL_16 = 3'b001;
parameter MAC_16 = 3'b010;
parameter SAT_16 = 3'b011;
parameter MUL_8  = 3'b101;
parameter MAC_8  = 3'b110;
parameter SAT_8  = 3'b111;

parameter NO_STALL = 0;
parameter STALL    = 1;
// -----------------------------------------------------------------------------
// Constant declarations
// -----------------------------------------------------------------------------

// -----------------------------------------------------------------------------
// Signal declarations
// -----------------------------------------------------------------------------

reg             reset_n;
reg             clk;
reg             stall;
reg [2:0]       instruction;
reg [15:0]      multiplier;
reg [15:0]      multiplicand;

// Beginning of automatic wires (for instantiated-module outputs)
wire [7:0]		protect;		// From u_mac of mac.v, ...
wire [31:0]		result;			// From u_mac of mac.v, ...
reg [7:0]		protect_g;		// From u_mac of mac.v, ...
reg [31:0]		result_g;		// From u_mac of mac.v, ...


// End of automatics

// ========================= Start of Main Code ================================
mac u_mac(/*autoinst*/
        // Outputs
        .result			(result[31:0]),
        .protect			(protect[7:0]),
        // Inputs
        .reset_n			(reset_n),
        .clk			(clk),
        .multiplier			(multiplier[15:0]),
        .multiplicand		(multiplicand[15:0]),
        .instruction		(instruction[2:0]),
        .stall			(stall));

//---- clock generation
always
begin
    #(`HPHASE) clk = 1'b0;
    #(`HPHASE) clk = 1'b1;
end

reg [31:0] cycle_cnt;

always @(posedge clk or negedge reset_n)
    if(~reset_n)
        cycle_cnt <= 0;
    else
        cycle_cnt <= cycle_cnt + 1'b1;

integer result_file1;
integer result_file2;
reg  [39:0] data_base [0:85];
initial
    $readmemh("EXPECT.DAT", data_base);

integer i;
reg    [39:0] data_tmp;
reg    [9:0]  error_cnt;
reg     ready;

initial
begin
    error_cnt = 0;
    @(negedge clk); // start to compare from 2nd cycle
    for  (i = 1; i <= 86; i = i + 1)
    begin
        data_tmp = data_base[i-1];
        @(negedge clk);
        if (protect !== data_tmp[39:32])
        begin
            $display ("ERROR at cycle_cnt= %d: protect(%h)!= EXPECT(%h)",
                      cycle_cnt, protect, data_tmp[39:32]);
            error_cnt = error_cnt + 1;
        end
        if (result !== data_tmp[31:0])
        begin
            $display ("ERROR at cycle_cnt= %d: result(%h)!= EXPECT(%h)",
                      cycle_cnt,  result, data_tmp[31:0]);
            error_cnt = error_cnt + 1;
        end
    end

    if(error_cnt == 10'b0)
    begin
        $display ("=================================================");
        $display ("Congratulation!, Your design PASSed all the test patterns ");
        $display ("=================================================");
    end
    else
    begin
        $display ("=================================================");
        $display ("There're %d errors in your design", error_cnt);
        $display ("=================================================");
    end
end

/*
initial 
  $sdf_annotate ("chip.sdf", u_mac);
*/


initial
begin
    /*  result_file1 = $fopen("mac_rst.txt"); */
    /*    result_file2 = $fopen("EXPECT.DAT");    */
    dump_vcd;
    #0
     clk = 1;
    reset_n = 1;
    stall = 1'b0;
    multiplier = 16'bz;
    multiplicand = 16'bz;
    instruction = 3'bz;
    error_cnt = 0;
    ready     = 0;
    $display("start test");
    #(`HPHASE)
     reset_n = 0;
    #(`CYCLE-0.1)  // to prevent from race condition by ccyang
     reset_n = 1;
    test_mac_16;
    test_mac_8;
    #(3* `CYCLE)
     $finish;
end

task test_mac_8;
    begin
        //********************
        mac_tsk(CLEAR, NO_STALL, 16'hff11, 16'h11ff, 0, 0);

        $display("------------------------------");
        $display("b1. test MUL_8, cycle = %h", cycle_cnt);
        mac_tsk(MUL_8, NO_STALL, 16'h7f7f, 16'h7f7f, protect_g, result_g);
        mac_tsk(MUL_8, NO_STALL, 16'h8080, 16'h8080, protect_g, result_g);
        mac_tsk(MUL_8, NO_STALL, 16'h7f7f, 16'h8080, protect_g, result_g);
        mac_tsk(MUL_8, NO_STALL, 16'h3031, 16'h232f, protect_g, result_g);

        $display("------------------------------");
        $display("b2. test MAC_8, overflow, cycle = %h", cycle_cnt);
        mac_tsk(MAC_8, NO_STALL, 16'h7f7f, 16'h7f7f, protect_g, result_g);
        mac_tsk(MAC_8, NO_STALL, 16'h7f7f, 16'h7f7f, protect_g, result_g);
        mac_tsk(MAC_8, NO_STALL, 16'h7f7f, 16'h7f7f, protect_g, result_g);

        mac_tsk(SAT_8, NO_STALL, 16'h8080, 16'h8080, protect_g, result_g);

        mac_tsk(MAC_8, NO_STALL, 16'h7f7f, 16'h7f7f, protect_g, result_g);
        mac_tsk(MAC_8, NO_STALL, 16'h7f7f, 16'h7f7f, protect_g, result_g);
        mac_tsk(MAC_8, NO_STALL, 16'h7f7f, 16'h7f7f, protect_g, result_g);
        mac_tsk(MAC_8, NO_STALL, 16'h7f7f, 16'h7f7f, protect_g, result_g);
        mac_tsk(MAC_8, NO_STALL, 16'h7f7f, 16'h7f7f, protect_g, result_g);
        mac_tsk(MAC_8, NO_STALL, 16'h7f7f, 16'h7f7f, protect_g, result_g);
        mac_tsk(MAC_8, NO_STALL, 16'h7f7f, 16'h7f7f, protect_g, result_g);
        mac_tsk(MAC_8, NO_STALL, 16'h7f7f, 16'h7f7f, protect_g, result_g);

        $display("------------------------------");
        $display("b3. test stall, cycle = %h", cycle_cnt);
        mac_tsk(SAT_8,    STALL,    16'h8080, 16'h8080, protect_g, result_g);
        mac_tsk(SAT_8,    NO_STALL, 16'h8080, 16'h8080, protect_g, result_g);

        $display("------------------------------");
        $display("b4. test SAT_8, cycle = %h", cycle_cnt);
        mac_tsk(SAT_8, NO_STALL, 16'h8080, 16'h8080, protect_g, result_g);
        mac_tsk(CLEAR, NO_STALL, 16'hff11, 16'h11ff, protect_g, result_g);

        $display("------------------------------");
        $display("b5. test MAC_8, cycle = %h", cycle_cnt);
        mac_tsk(MAC_8, NO_STALL, 16'h807f, 16'h7f7f, protect_g, result_g);
        mac_tsk(MAC_8, NO_STALL, 16'h807f, 16'h7f7f, protect_g, result_g);
        mac_tsk(MAC_8, NO_STALL, 16'h807f, 16'h7f7f, protect_g, result_g);

        mac_tsk(SAT_8, NO_STALL, 16'h807f, 16'h8080, protect_g, result_g);

        mac_tsk(MAC_8, NO_STALL, 16'h807f, 16'h7f7f, protect_g, result_g);
        mac_tsk(MAC_8, NO_STALL, 16'h807f, 16'h7f7f, protect_g, result_g);
        mac_tsk(MAC_8, NO_STALL, 16'h807f, 16'h7f7f, protect_g, result_g);
        mac_tsk(MAC_8, NO_STALL, 16'h807f, 16'h7f7f, protect_g, result_g);
        mac_tsk(MAC_8, NO_STALL, 16'h807f, 16'h7f7f, protect_g, result_g);
        mac_tsk(MAC_8, NO_STALL, 16'h807f, 16'h7f7f, protect_g, result_g);
        mac_tsk(MAC_8, NO_STALL, 16'h807f, 16'h7f7f, protect_g, result_g);
        mac_tsk(MAC_8, NO_STALL, 16'h807f, 16'h7f7f, protect_g, result_g);

        $display("------------------------------");
        $display("b6. stall insertion, cycle = %h", cycle_cnt);
        mac_tsk(SAT_8,    STALL, 16'h8080, 16'h8080, protect_g, result_g);
        mac_tsk(SAT_8,    STALL, 16'h8080, 16'h8080, protect_g, result_g);
        mac_tsk(SAT_8, NO_STALL, 16'h8080, 16'h8080, protect_g, result_g);
        mac_tsk(SAT_8, NO_STALL, 16'h8080, 16'h8080, protect_g, result_g);
        mac_tsk(MAC_8, NO_STALL, 16'h8080, 16'h7f7f, protect_g, result_g);

        $display("b7. test stall, cycle = %h", cycle_cnt);
        mac_tsk(SAT_8,      STALL, 16'h8080, 16'h8080, protect_g, result_g);
        mac_tsk(SAT_8,   NO_STALL, 16'h8080, 16'h8080, protect_g, result_g);

        $display("b8. test SAT_8, cycle = %h", cycle_cnt);
        mac_tsk(SAT_8, NO_STALL, 16'h8080, 16'h8080, protect_g, result_g);
        mac_tsk(CLEAR, NO_STALL, 16'hff11, 16'h11ff, protect_g, result_g);

        //********************
    end
endtask

task test_mac_16;
    begin
        //********************
        mac_tsk(CLEAR, NO_STALL, 16'hff11, 16'h11ff, 0, 0);

        $display("------------------------------");
        $display("a1. test MUL_16, cycle = %h", cycle_cnt);
        mac_tsk(MUL_16, NO_STALL, 16'h7fff, 16'h7fff, protect_g, result_g);
        mac_tsk(MUL_16, NO_STALL, 16'h8000, 16'h8000, protect_g, result_g);
        mac_tsk(MUL_16, NO_STALL, 16'h7fff, 16'h8000, protect_g, result_g);
        mac_tsk(MUL_16, NO_STALL, 16'h3031, 16'h232f, protect_g, result_g);

        $display("------------------------------");
        $display("a2. test MAC_16, overflow, cycle = %h", cycle_cnt);
        mac_tsk(MAC_16, NO_STALL, 16'h7fff, 16'h7fff, protect_g, result_g);
        mac_tsk(MAC_16, NO_STALL, 16'h7fff, 16'h7fff, protect_g, result_g);
        mac_tsk(MAC_16, NO_STALL, 16'h7fff, 16'h7fff, protect_g, result_g);

        mac_tsk(SAT_16, NO_STALL, 16'h8000, 16'h8000, protect_g, result_g);

        mac_tsk(MAC_16, NO_STALL, 16'h7fff, 16'h7fff, protect_g, result_g);
        mac_tsk(MAC_16, NO_STALL, 16'h7fff, 16'h7fff, protect_g, result_g);
        mac_tsk(MAC_16, NO_STALL, 16'h7fff, 16'h7fff, protect_g, result_g);
        mac_tsk(MAC_16, NO_STALL, 16'h7fff, 16'h7fff, protect_g, result_g);
        mac_tsk(MAC_16, NO_STALL, 16'h7fff, 16'h7fff, protect_g, result_g);
        mac_tsk(MAC_16, NO_STALL, 16'h7fff, 16'h7fff, protect_g, result_g);
        mac_tsk(MAC_16, NO_STALL, 16'h7fff, 16'h7fff, protect_g, result_g);
        mac_tsk(MAC_16, NO_STALL, 16'h7fff, 16'h7fff, protect_g, result_g);

        $display("------------------------------");
        $display("a3. test stall, cycle = %h", cycle_cnt);
        mac_tsk(SAT_16,    STALL, 16'h8000, 16'h8000, protect_g, result_g);
        mac_tsk(SAT_16, NO_STALL, 16'h8000, 16'h8000, protect_g, result_g);

        $display("------------------------------");
        $display("a4. test SAT_16, cycle = %h", cycle_cnt);
        mac_tsk(SAT_16, NO_STALL, 16'h8000, 16'h8000, protect_g, result_g);
        mac_tsk(CLEAR,  NO_STALL, 16'hff11, 16'h11ff, protect_g, result_g);

        $display("------------------------------");
        $display("a5. test MAC_16, cycle = %h", cycle_cnt);
        mac_tsk(MAC_16, NO_STALL, 16'h8000, 16'h7fff, protect_g, result_g);
        mac_tsk(MAC_16, NO_STALL, 16'h8000, 16'h7fff, protect_g, result_g);
        mac_tsk(MAC_16, NO_STALL, 16'h8000, 16'h7fff, protect_g, result_g);

        mac_tsk(SAT_16, NO_STALL, 16'h8000, 16'h8000, protect_g, result_g);

        mac_tsk(MAC_16, NO_STALL, 16'h8000, 16'h7fff, protect_g, result_g);
        mac_tsk(MAC_16, NO_STALL, 16'h8000, 16'h7fff, protect_g, result_g);
        mac_tsk(MAC_16, NO_STALL, 16'h8000, 16'h7fff, protect_g, result_g);
        mac_tsk(MAC_16, NO_STALL, 16'h8000, 16'h7fff, protect_g, result_g);
        mac_tsk(MAC_16, NO_STALL, 16'h8000, 16'h7fff, protect_g, result_g);
        mac_tsk(MAC_16, NO_STALL, 16'h8000, 16'h7fff, protect_g, result_g);
        mac_tsk(MAC_16, NO_STALL, 16'h8000, 16'h7fff, protect_g, result_g);
        mac_tsk(MAC_16, NO_STALL, 16'h8000, 16'h7fff, protect_g, result_g);

        $display("------------------------------");
        $display("a6. stall insertion, cycle = %h", cycle_cnt);
        mac_tsk(SAT_16,    STALL, 16'h8000, 16'h8000, protect_g, result_g);
        mac_tsk(SAT_16,    STALL, 16'h8000, 16'h8000, protect_g, result_g);
        mac_tsk(SAT_16, NO_STALL, 16'h8000, 16'h8000, protect_g, result_g);
        mac_tsk(SAT_16,    STALL, 16'h8000, 16'h8000, protect_g, result_g);
        mac_tsk(MAC_16, NO_STALL, 16'h8000, 16'h7fff, protect_g, result_g);

        $display("a7. test stall, cycle = %h", cycle_cnt);
        mac_tsk(SAT_16,    STALL, 16'h8000, 16'h8000, protect_g, result_g);

        $display("a8. test SAT_16, cycle = %h", cycle_cnt);
        mac_tsk(SAT_16, NO_STALL, 16'h8000, 16'h8000, protect_g, result_g);
        mac_tsk(CLEAR,  NO_STALL, 16'hff11, 16'h11ff, protect_g, result_g);

        //********************

    end
endtask

task mac_tsk;
    input [2:0] instruction_t;
    input stall_t;
    input [15:0] a;
    input [15:0] b;

    input [7:0] protect_t; //unused, for on-line verification
    input [31:0] result_t; //unused, for on-line verification

    begin
        @(negedge clk)
         #(`CYCLE*0.3)
         instruction = instruction_t;
        multiplier = a;
        multiplicand = b;
        stall = stall_t;
        protect_g = protect_t;
        result_g = result_t;
        #(`CYCLE*0.4)
         instruction = 3'bz;
        multiplier = 16'bz;
        multiplicand = 16'bz;
        stall = 1'b0;
        protect_g = protect_t;
        result_g = result_t;
    end
endtask

//*********************
//compare result
//*********************
always @(negedge clk)
begin
    //  $fdisplay(result_file1,"cycles = %h,  %h,  %h", cycle_cnt, protect, result);
    //    $fdisplay(result_file2,"%h%h", protect, result);
end

//*********************
// Dump waveform
//*********************

task dump_vcd;
    begin
        $dumpfile("mac.vcd");
        $dumpvars;
`ifdef FSDB

        $fsdbVersion;
        $fsdbDumpfile(`DUMPFILE_NAME);
        $fsdbDumpvars;
`endif

    end
endtask

endmodule // module_name

          // ============================ End of Module ==================================
          // Revision History
          // $Log: dic_2003.v,v $
          // Revision 1.1  2003/04/25 04:01:19  ip01_11a
          // for ic test
          //
          // Revision 1.1.1.1  2003/04/15 03:30:42  ip01_11a
          // first version
          //

hw3/mac.vcd
$date
	Sat Nov 04 23:05:22 2023
$end
$version
	ModelSim Version 2020.1
$end
$timescale
	10ps
$end

$scope module mac_sim $end
$var parameter 3 ! CLEAR $end
$var parameter 3 " CLEAR2 $end
$var parameter 3 # MUL_16 $end
$var parameter 3 $ MAC_16 $end
$var parameter 3 % SAT_16 $end
$var parameter 3 & MUL_8 $end
$var parameter 3 ' MAC_8 $end
$var parameter 3 ( SAT_8 $end
$var parameter 32 ) NO_STALL $end
$var parameter 32 * STALL $end
$var reg 1 + reset_n $end
$var reg 1 , clk $end
$var reg 1 - stall $end
$var reg 3 . instruction [2:0] $end
$var reg 16 / multiplier [15:0] $end
$var reg 16 0 multiplicand [15:0] $end
$var wire 1 1 protect [7] $end
$var wire 1 2 protect [6] $end
$var wire 1 3 protect [5] $end
$var wire 1 4 protect [4] $end
$var wire 1 5 protect [3] $end
$var wire 1 6 protect [2] $end
$var wire 1 7 protect [1] $end
$var wire 1 8 protect [0] $end
$var wire 1 9 result [31] $end
$var wire 1 : result [30] $end
$var wire 1 ; result [29] $end
$var wire 1 < result [28] $end
$var wire 1 = result [27] $end
$var wire 1 > result [26] $end
$var wire 1 ? result [25] $end
$var wire 1 @ result [24] $end
$var wire 1 A result [23] $end
$var wire 1 B result [22] $end
$var wire 1 C result [21] $end
$var wire 1 D result [20] $end
$var wire 1 E result [19] $end
$var wire 1 F result [18] $end
$var wire 1 G result [17] $end
$var wire 1 H result [16] $end
$var wire 1 I result [15] $end
$var wire 1 J result [14] $end
$var wire 1 K result [13] $end
$var wire 1 L result [12] $end
$var wire 1 M result [11] $end
$var wire 1 N result [10] $end
$var wire 1 O result [9] $end
$var wire 1 P result [8] $end
$var wire 1 Q result [7] $end
$var wire 1 R result [6] $end
$var wire 1 S result [5] $end
$var wire 1 T result [4] $end
$var wire 1 U result [3] $end
$var wire 1 V result [2] $end
$var wire 1 W result [1] $end
$var wire 1 X result [0] $end
$var reg 8 Y protect_g [7:0] $end
$var reg 32 Z result_g [31:0] $end
$var reg 32 [ cycle_cnt [31:0] $end
$var integer 32 \ result_file1 $end
$var integer 32 ] result_file2 $end
$var integer 32 ^ i $end
$var reg 40 _ data_tmp [39:0] $end
$var reg 10 ` error_cnt [9:0] $end
$var reg 1 a ready $end

$scope task test_mac_8 $end
$upscope $end

$scope task test_mac_16 $end
$upscope $end

$scope task mac_tsk $end
$var reg 3 b instruction_t [2:0] $end
$var reg 1 c stall_t $end
$var reg 16 d a [15:0] $end
$var reg 16 e b [15:0] $end
$var reg 8 f protect_t [7:0] $end
$var reg 32 g result_t [31:0] $end
$upscope $end

$scope task dump_vcd $end
$upscope $end

$scope module u_mac $end
$var wire 1 h clk $end
$var wire 1 i reset_n $end
$var wire 1 j instruction [2] $end
$var wire 1 k instruction [1] $end
$var wire 1 l instruction [0] $end
$var wire 1 m multiplier [15] $end
$var wire 1 n multiplier [14] $end
$var wire 1 o multiplier [13] $end
$var wire 1 p multiplier [12] $end
$var wire 1 q multiplier [11] $end
$var wire 1 r multiplier [10] $end
$var wire 1 s multiplier [9] $end
$var wire 1 t multiplier [8] $end
$var wire 1 u multiplier [7] $end
$var wire 1 v multiplier [6] $end
$var wire 1 w multiplier [5] $end
$var wire 1 x multiplier [4] $end
$var wire 1 y multiplier [3] $end
$var wire 1 z multiplier [2] $end
$var wire 1 { multiplier [1] $end
$var wire 1 | multiplier [0] $end
$var wire 1 } multiplicand [15] $end
$var wire 1 ~ multiplicand [14] $end
$var wire 1 !! multiplicand [13] $end
$var wire 1 "! multiplicand [12] $end
$var wire 1 #! multiplicand [11] $end
$var wire 1 $! multiplicand [10] $end
$var wire 1 %! multiplicand [9] $end
$var wire 1 &! multiplicand [8] $end
$var wire 1 '! multiplicand [7] $end
$var wire 1 (! multiplicand [6] $end
$var wire 1 )! multiplicand [5] $end
$var wire 1 *! multiplicand [4] $end
$var wire 1 +! multiplicand [3] $end
$var wire 1 ,! multiplicand [2] $end
$var wire 1 -! multiplicand [1] $end
$var wire 1 .! multiplicand [0] $end
$var wire 1 /! stall $end
$var reg 8 0! protect [7:0] $end
$var reg 32 1! result [31:0] $end
$var reg 16 2! Multiplier [15:0] $end
$var reg 16 3! Multiplicand [15:0] $end
$var reg 40 4! temp [39:0] $end
$var reg 40 5! temp2 [39:0] $end
$var reg 2 6! notice [1:0] $end
$var reg 2 7! notice1 [1:0] $end
$var reg 40 8! temp3 [39:0] $end
$var integer 32 9! i $end
$upscope $end
$upscope $end
$enddefinitions $end
#0
$dumpvars
1+
1,
0-
bz .
bz /
bz 0
bx Y
bx Z
bx 0!
bx 1!
bz 2!
bz 3!
bx 4!
bx 5!
bx 6!
bx 7!
bx 8!
bx [
bx _
b0 `
0a
bx b
xc
bx d
bx e
bx f
bx g
b0 !
b100 "
b1 #
b10 $
b11 %
b101 &
b110 '
b111 (
b0 )
b1 *
bx 9!
bx \
bx ]
bx ^
x8
x7
x6
x5
x4
x3
x2
x1
xX
xW
xV
xU
xT
xS
xR
xQ
xP
xO
xN
xM
xL
xK
xJ
xI
xH
xG
xF
xE
xD
xC
xB
xA
x@
x?
x>
x=
x<
x;
x:
x9
0/!
zl
zk
zj
z.!
z-!
z,!
z+!
z*!
z)!
z(!
z'!
z&!
z%!
z$!
z#!
z"!
z!!
z~
z}
z|
z{
zz
zy
zx
zw
zv
zu
zt
zs
zr
zq
zp
zo
zn
zm
1h
1i
$end
#1000
0,
0+
0h
0i
b0 0!
b0 1!
b0 4!
b1 ^
b0 _
0X
0W
0V
0U
0T
0S
0R
0Q
0P
0O
0N
0M
0L
0K
0J
0I
0H
0G
0F
0E
0D
0C
0B
0A
0@
0?
0>
0=
0<
0;
0:
09
08
07
06
05
04
03
02
01
b0 [
#2000
1,
1h
#2990
1+
b0 b
0c
b1111111100010001 d
b1000111111111 e
b0 f
b0 g
1i
#3000
0,
0h
b10 ^
#3600
b0 .
b1111111100010001 /
b1000111111111 0
b0 Y
b0 Z
1.!
1-!
1,!
1+!
1*!
1)!
1(!
1'!
1&!
0%!
0$!
0#!
1"!
0!!
0~
0}
1|
0{
0z
0y
1x
0w
0v
0u
1t
1s
1r
1q
1p
1o
1n
1m
0l
0k
0j
#4000
1,
1h
b1111111100010001 2!
b1000111111111 3!
b1 [
#4400
bz .
bz /
bz 0
b1 b
b111111111111111 d
b111111111111111 e
z.!
z-!
z,!
z+!
z*!
z)!
z(!
z'!
z&!
z%!
z$!
z#!
z"!
z!!
z~
z}
z|
z{
zz
zy
zx
zw
zv
zu
zt
zs
zr
zq
zp
zo
zn
zm
zl
zk
zj
#5000
0,
0h
b11 ^
#5600
b1 .
b111111111111111 /
b111111111111111 0
1.!
1-!
1,!
1+!
1*!
1)!
1(!
1'!
1&!
1%!
1$!
1#!
1"!
1!!
1~
0}
1|
1{
1z
1y
1x
1w
1v
1u
1t
1s
1r
1q
1p
1o
1n
0m
1l
0k
0j
#6000
1,
1h
b111111111111111 2!
b111111111111111 3!
b0 6!
b111111111111110000000000000001 4!
b10 [
#6400
bz .
bz /
bz 0
b1000000000000000 d
b1000000000000000 e
z.!
z-!
z,!
z+!
z*!
z)!
z(!
z'!
z&!
z%!
z$!
z#!
z"!
z!!
z~
z}
z|
z{
zz
zy
zx
zw
zv
zu
zt
zs
zr
zq
zp
zo
zn
zm
zl
zk
zj
#7000
0,
0h
b100 ^
#7600
b1 .
b1000000000000000 /
b1000000000000000 0
0.!
0-!
0,!
0+!
0*!
0)!
0(!
0'!
0&!
0%!
0$!
0#!
0"!
0!!
0~
1}
0|
0{
0z
0y
0x
0w
0v
0u
0t
0s
0r
0q
0p
0o
0n
1m
1l
0k
0j
#8000
1,
1h
b1000000000000000 2!
b1000000000000000 3!
b1 6!
b10 6!
b1000000000000000000000000000000 4!
b11 [
#8400
bz .
bz /
bz 0
b111111111111111 d
z.!
z-!
z,!
z+!
z*!
z)!
z(!
z'!
z&!
z%!
z$!
z#!
z"!
z!!
z~
z}
z|
z{
zz
zy
zx
zw
zv
zu
zt
zs
zr
zq
zp
zo
zn
zm
zl
zk
zj
#9000
0,
0h
b101 ^
b111111111111110000000000000001 _
#9600
b1 .
b111111111111111 /
b1000000000000000 0
0.!
0-!
0,!
0+!
0*!
0)!
0(!
0'!
0&!
0%!
0$!
0#!
0"!
0!!
0~
1}
1|
1{
1z
1y
1x
1w
1v
1u
1t
1s
1r
1q
1p
1o
1n
0m
1l
0k
0j
#10000
1,
1h
b111111111111111 2!
b0 6!
b1 6!
b111111111111111000000000000000 4!
b1111111111000000000000001000000000000000 4!
b111111111111110000000000000001 1!
1X
1H
1G
1F
1E
1D
1C
1B
1A
1@
1?
1>
1=
1<
1;
b100 [
#10400
bz .
bz /
bz 0
b11000000110001 d
b10001100101111 e
z.!
z-!
z,!
z+!
z*!
z)!
z(!
z'!
z&!
z%!
z$!
z#!
z"!
z!!
z~
z}
z|
z{
zz
zy
zx
zw
zv
zu
zt
zs
zr
zq
zp
zo
zn
zm
zl
zk
zj
#11000
0,
0h
b110 ^
b1000000000000000000000000000000 _
