CS_stud/CS_stud.v
`timescale 1ns/10ps
module CS(Y, X, reset, clk, appr, avg);
input clk, reset;
input [7:0] X;
output reg [9:0] Y;
output reg [7:0] appr;
output reg [7:0] avg;

reg [7:0] queue [0:8];
// for storing the 9 input items, 8-bit item
reg [11:0] sum;
// for storig the sum of 9 items
reg [7:0] temp;
reg [10:0] min;

integer i;

always@(posedge clk or posedge reset)
begin
    if (reset == 1'b1)
    begin

        for (i=0; i<9; i=i+1'b1)
            queue[i]=0;
        avg=0;
        appr=0;
        sum=0;
        min=8'b11111111;

        temp=0;

    end
    else
    begin
        avg=0;
        appr=0;
        sum=0;
        min=8'b11111111;
        temp=0;
        for (i=0; i<8; i=i+1'b1)
        begin
            queue[i]=queue[i+1];// shift the stored item
            sum=sum+queue[i];// sum up the first 8 items

        end
        // store the new input item
        queue[8]=X;
        // add the 9th item

        avg=(sum+queue[8])/9;
        // calculate the average

        for (i=0; i<9; i=i+1'b1)
        begin
            if(queue[i]<=avg)
            begin
                temp=avg-queue[i];
                if(temp<=min)
                begin
                    appr=queue[i];
                    min=temp;
                end

            end




        end
        // find the approximate average

        #5;
        Y=(sum+queue[8]+9*appr)/8;
        // calaulate the output
        // divided by 8
    end
end
endmodule

CS_stud/testfixture.v
`timescale 1ns/10ps
`define CYCLE  10        	// Modify your clock period here
`define SDFFILE "cs_syn.sdf"	// Modify your sdf file name here
`define INFILE "in.dat"
`define OUTFILE "out_golden.dat"  

module test;
parameter INPUT_DATA = `INFILE;
parameter GOLDEN = `OUTFILE;
parameter N_PAT = 2000;
parameter t_reset = `CYCLE*2;

reg reset;
reg clk;
reg ready;
reg stop;
reg flag1, flag2;
wire pclk = clk ;

integer i, out_f, err, pattern_num;
integer a, b;
reg     [7:0] X;
reg 	[7:0] data_base1 [0:20000];
reg	[9:0] data_base2 [0:20000];
reg 	[9:0] data_tmp;
wire    [9:0] Y; 

wire [7:0] appr, avg;//for debug only
CS top (.Y(Y), .X(X), .reset(reset), .clk(clk), .appr(appr), .avg(avg)); 

//initial $sdf_annotate(`SDFFILE, top);

initial	$readmemh (INPUT_DATA, data_base1);

initial $readmemh (GOLDEN, data_base2);

initial begin
   reset = 1'b0;
   clk = 1'b1;
   stop = 1'b0;
   err = 0;
   a = 0;
   b = 0;
   pattern_num = 0 ;     
end

initial begin
$dumpfile("cs.vcd");
$dumpvars;
//$fsdbDumpfile("cs.fsdb");
//$fsdbDumpvars; 

   out_f = $fopen("out.dat");
   if (out_f == 0) begin
        $display("Output file open error !");
        $finish;
   end
end

always begin #(`CYCLE/2) clk = ~clk;
end


specify
$setup(Y, posedge pclk, 0.5, flag1);
$hold(posedge pclk, Y, 0.5, flag2); 
endspecify 

always @(flag1)
   if(flag1 == 1'b1 || flag1 == 1'b0)
     a = a +1;

always @(flag2)
   if(flag2 == 1'b1  || flag2 == 1'b0)
     b = b +1;


initial 
  begin
    X = data_base1[0] ;
    @(negedge clk) reset = 1'b1;
    #t_reset reset = 1'b0;  ready = 1'b0;
    #`CYCLE
    for (i = 1; i < N_PAT; i = i + 1) 
    begin
      @(negedge clk) X = data_base1[i]; 
      if (i==8)
        @(posedge clk) ready = 1'b1;                      
    end 
  end  
 		
always @(posedge clk) 
  begin
   if (pattern_num + 9 > N_PAT)      stop = 1 ;
   else if (ready) 
     begin
       data_tmp = data_base2[pattern_num]; 
       $fdisplay(out_f,"%h", Y); 
         if (Y !== data_tmp) 
           begin
             $display("ERROR at %d:output %h !=expect %h ",pattern_num, Y, data_tmp);
             err = err + 1 ;
           end
       pattern_num = pattern_num + 1 ; 
     end

  end  

initial begin
      @(posedge stop)
      $display("---------------------------------------------\n");
      if (a !=0)
         $display("There are %d setup time violations by Y\n", a);
      if (b !=0)
         $display("There are %d hold time violations by Y\n", b);
      $display("---------------------------------------------\n");
      if (err == 0)
        begin
          $display("All data have been generated successfully!\n");
          $display("-------------------PASS-------------------\n");
        end
      else 
         $display("There are %d errors!\n", err);
      $display("---------------------------------------------\n");
      $finish;
   end
endmodule

CS_stud/cs.vcd
$date
	Wed Nov 15 11:33:11 2023
$end
$version
	ModelSim Version 2020.1
$end
$timescale
	10ps
$end

$scope module test $end
$var parameter 48 ! INPUT_DATA $end
$var parameter 112 " GOLDEN $end
$var parameter 32 # N_PAT $end
$var parameter 32 $ t_reset $end
$var reg 1 % reset $end
$var reg 1 & clk $end
$var reg 1 ' ready $end
$var reg 1 ( stop $end
$var reg 1 ) flag1 $end
$var reg 1 * flag2 $end
$var wire 1 + pclk $end
$var integer 32 , i $end
$var integer 32 - out_f $end
$var integer 32 . err $end
$var integer 32 / pattern_num $end
$var integer 32 0 a $end
$var integer 32 1 b $end
$var reg 8 2 X [7:0] $end
$var reg 10 3 data_tmp [9:0] $end
$var wire 1 4 Y [9] $end
$var wire 1 5 Y [8] $end
$var wire 1 6 Y [7] $end
$var wire 1 7 Y [6] $end
$var wire 1 8 Y [5] $end
$var wire 1 9 Y [4] $end
$var wire 1 : Y [3] $end
$var wire 1 ; Y [2] $end
$var wire 1 < Y [1] $end
$var wire 1 = Y [0] $end
$var wire 1 > appr [7] $end
$var wire 1 ? appr [6] $end
$var wire 1 @ appr [5] $end
$var wire 1 A appr [4] $end
$var wire 1 B appr [3] $end
$var wire 1 C appr [2] $end
$var wire 1 D appr [1] $end
$var wire 1 E appr [0] $end
$var wire 1 F avg [7] $end
$var wire 1 G avg [6] $end
$var wire 1 H avg [5] $end
$var wire 1 I avg [4] $end
$var wire 1 J avg [3] $end
$var wire 1 K avg [2] $end
$var wire 1 L avg [1] $end
$var wire 1 M avg [0] $end

$scope module top $end
$var wire 1 N clk $end
$var wire 1 O reset $end
$var wire 1 P X [7] $end
$var wire 1 Q X [6] $end
$var wire 1 R X [5] $end
$var wire 1 S X [4] $end
$var wire 1 T X [3] $end
$var wire 1 U X [2] $end
$var wire 1 V X [1] $end
$var wire 1 W X [0] $end
$var reg 10 X Y [9:0] $end
$var reg 8 Y appr [7:0] $end
$var reg 8 Z avg [7:0] $end
$var reg 12 [ sum [11:0] $end
$var reg 8 \ temp [7:0] $end
$var reg 11 ] min [10:0] $end
$var integer 32 ^ i $end
$upscope $end
$upscope $end
$enddefinitions $end
#0
$dumpvars
0%
1&
x'
0(
x)
x*
b10001111 2
bx 3
bx X
b0 Y
bx Z
bx [
b0 \
b11111111 ]
b11111010000 #
b10100 $
b11010010110111000101110011001000110000101110100 !
b110111101110101011101000101111101100111011011110110110001100100011001010110111000101110011001000110000101110100 "
bx ,
b10 -
b0 .
b0 /
b0 0
b0 1
b1001 ^
1+
x=
x<
x;
x:
x9
x8
x7
x6
x5
x4
0E
0D
0C
0B
0A
0@
0?
0>
xM
xL
xK
xJ
xI
xH
xG
xF
1N
0O
1W
1V
1U
1T
0S
0R
0Q
1P
$end
#500
0&
0+
0N
1%
1O
b0 ^
b1 ^
b10 ^
b11 ^
b100 ^
b101 ^
b110 ^
b111 ^
b1000 ^
b1001 ^
b0 Z
b0 [
0M
0L
0K
0J
0I
0H
0G
0F
#1000
1&
1+
1N
b0 ^
b1 ^
b10 ^
b11 ^
b100 ^
b101 ^
b110 ^
b111 ^
b1000 ^
b1001 ^
#1500
0&
0+
0N
#2000
1&
1+
1N
b0 ^
b1 ^
b10 ^
b11 ^
b100 ^
b101 ^
b110 ^
b111 ^
b1000 ^
b1001 ^
#2500
0%
0'
0&
0+
0O
0N
#3000
1&
1+
1N
b0 ^
b1 ^
b10 ^
b11 ^
b100 ^
b101 ^
b110 ^
b111 ^
b1000 ^
b1111 Z
b0 ^
b1111 \
b1111 ]
b1 ^
b10 ^
b11 ^
b100 ^
b101 ^
b110 ^
b111 ^
b1000 ^
b1001 ^
1M
1L
1K
1J
#3500
b1 ,
0&
b10001 X
0+
1=
0<
0;
0:
19
08
07
06
05
04
0N
b1011 2
b10 ,
0U
0P
#4000
1&
1+
1N
b0 Z
b11111111 ]
b0 \
b0 ^
b1 ^
b10 ^
b11 ^
b100 ^
b101 ^
b110 ^
b111 ^
b10001111 [
b1000 ^
b10001 Z
b0 ^
b10001 \
b10001 ]
b1 ^
b10 ^
b11 ^
b100 ^
b101 ^
b110 ^
b111 ^
b1000 ^
b110 \
b1011 Y
b110 ]
b1001 ^
1E
1D
1B
0L
0K
0J
1I
#4500
0&
b11111 X
0+
1<
1;
1:
0N
b1011101 2
b11 ,
0V
1U
1S
1Q
#5000
1&
1+
1N
b0 Z
b0 Y
b0 [
b11111111 ]
b0 \
b0 ^
b1 ^
b10 ^
b11 ^
b100 ^
b101 ^
b110 ^
b10001111 [
b111 ^
b10011010 [
b1000 ^
b11011 Z
b0 ^
b11011 \
b11011 ]
b1 ^
b10 ^
b11 ^
b100 ^
b101 ^
b110 ^
b111 ^
b10000 \
b1011 Y
b10000 ]
b1000 ^
b1001 ^
1L
1J
#5500
0&
b101011 X
0+
0;
09
18
0N
b100000 2
b100 ,
0W
0U
0T
0S
1R
0Q
#6000
1&
1+
1N
b0 Z
b0 Y
b0 [
b11111111 ]
b0 \
b0 ^
b1 ^
b10 ^
b11 ^
b100 ^
b101 ^
b10001111 [
b110 ^
b10011010 [
b111 ^
b11110111 [
b1000 ^
b11111 Z
b0 ^
b11111 \
b11111 ]
b1 ^
b10 ^
b11 ^
b100 ^
b101 ^
b110 ^
b10100 \
b1011 Y
b10100 ]
b111 ^
b1000 ^
b1001 ^
1K
#6500
0&
b101111 X
0+
1;
0N
b11110011 2
b101 ,
1W
1V
1S
1Q
1P
#7000
1&
1+
1N
b0 Z
b0 Y
b0 [
b11111111 ]
b0 \
b0 ^
b1 ^
b10 ^
b11 ^
b100 ^
b10001111 [
b101 ^
b10011010 [
b110 ^
b11110111 [
b111 ^
b100010111 [
b1000 ^
b111010 Z
b0 ^
b111010 \
b111010 ]
b1 ^
b10 ^
b11 ^
b100 ^
b101 ^
b101111 \
b1011 Y
b101111 ]
b110 ^
b111 ^
b11010 \
b100000 Y
b11010 ]
b1000 ^
b1001 ^
0E
0D
0B
1@
0M
0K
1H
#7500
0&
b1100101 X
0+
0<
0:
17
0N
b111110 2
b110 ,
0W
1U
1T
0Q
0P
#8000
1&
1+
1N
b0 Z
b0 Y
b0 [
b11111111 ]
b0 \
b0 ^
b1 ^
b10 ^
b11 ^
b10001111 [
b100 ^
b10011010 [
b101 ^
b11110111 [
b110 ^
b100010111 [
b111 ^
b1000001010 [
b1000 ^
b1000000 Z
b0 ^
b1000000 \
b1000000 ]
b1 ^
b10 ^
b11 ^
b100 ^
b110101 \
b1011 Y
b110101 ]
b101 ^
b110 ^
b100000 \
b100000 Y
b100000 ]
b111 ^
b1000 ^
b10 \
b111110 Y
b10 ]
b1001 ^
1D
1C
1B
1A
0L
0J
0I
0H
1G
#8500
0&
b10001110 X
0+
0=
1<
1:
08
07
16
0N
b11100101 2
b111 ,
1W
0V
0T
0S
1Q
1P
#9000
1&
1+
1N
b0 Z
b0 Y
b0 [
b11111111 ]
b0 \
b0 ^
b1 ^
b10 ^
b10001111 [
b11 ^
b10011010 [
b100 ^
b11110111 [
b101 ^
b100010111 [
b110 ^
b1000001010 [
b111 ^
b1001001000 [
b1000 ^
b1011010 Z
b0 ^
b1011010 \
b1011010 ]
b1 ^
b10 ^
b11 ^
b1001111 \
b1011 Y
b1001111 ]
b100 ^
b101 ^
b111010 \
b100000 Y
b111010 ]
b110 ^
b111 ^
b11100 \
b111110 Y
b11100 ]
b1000 ^
b1001 ^
1L
1J
1I
#9500
0&
b10101011 X
0+
1=
0;
18
0N
b11 2
b1000 ,
1V
0U
0R
0Q
0P
#10000
1&
1+
1N
b0 Z
b0 Y
b0 [
b11111111 ]
b0 \
b0 ^
b1 ^
b10001111 [
b10 ^
b10011010 [
b11 ^
b11110111 [
b100 ^
b100010111 [
b101 ^
b1000001010 [
b110 ^
b1001001000 [
b111 ^
b1100101101 [
b1000 ^
b1011010 Z
b0 ^
b1011010 \
b1011010 ]
b1 ^
b10 ^
b1001111 \
b1011 Y
b1001111 ]
b11 ^
b100 ^
b111010 \
b100000 Y
b111010 ]
b101 ^
b110 ^
b11100 \
b111110 Y
b11100 ]
b111 ^
b1000 ^
b1010111 \
b1001 ^
#10500
0&
0+
0N
b1100 2
0W
0V
1U
1T
#11000
1&
1+
1N
b0 Z
b0 Y
b0 [
b11111111 ]
b0 \
b0 ^
b10001111 [
b1 ^
b10011010 [
b10 ^
b11110111 [
b11 ^
b100010111 [
b100 ^
b1000001010 [
b101 ^
b1001001000 [
b110 ^
b1100101101 [
b111 ^
b1100110000 [
b1000 ^
b1011100 Z
b0 ^
b1 ^
b1010001 \
b1011 Y
b1010001 ]
b10 ^
b11 ^
b111100 \
b100000 Y
b111100 ]
b100 ^
b101 ^
b11110 \
b111110 Y
b11110 ]
b110 ^
b111 ^
b1011001 \
b1000 ^
b1010000 \
b1001 ^
1'
b1001 ,
0L
1K
#11500
0&
b10101101 X
0+
0<
1;
0N
b1110100 2
b1010 ,
0T
1S
1R
1Q
#12000
1&
1+
1N
b0 Z
b0 Y
b0 [
b11111111 ]
b0 \
b0 ^
b1011 [
b1 ^
b1101000 [
b10 ^
b10001000 [
b11 ^
b101111011 [
b100 ^
b110111001 [
b101 ^
b1010011110 [
b110 ^
b1010100001 [
b111 ^
b1010101101 [
b1000 ^
b1011001 Z
b0 ^
b1001110 \
b1011 Y
b1001110 ]
b1 ^
b10 ^
b111001 \
b100000 Y
b111001 ]
b11 ^
b100 ^
b11011 \
b111110 Y
b11011 ]
b101 ^
b110 ^
b1010110 \
b111 ^
b1001101 \
b1000 ^
b1001 ^
b10101101 3
b1 /
1M
0K
#12500
0&
b10101001 X
0+
0;
0N
b1111001 2
b1011 ,
1W
0U
1T
#13000
1&
1+
1N
b0 Z
b0 Y
b0 [
b11111111 ]
b0 \
b0 ^
b1011101 [
b1 ^
b1111101 [
b10 ^
b101110000 [
b11 ^
b110101110 [
b100 ^
b1010010011 [
b101 ^
b1010010110 [
b110 ^
b1010100010 [
b111 ^
b1100010110 [
b1000 ^
b1100101 Z
b0 ^
b1000 \
b1011101 Y
b1000 ]
b1 ^
b1000101 \
b10 ^
b11 ^
b100111 \
b100 ^
b101 ^
b1100010 \
b110 ^
b1011001 \
b111 ^
b1000 ^
b1001 ^
b10101001 3
b10 /
1E
0D
0@
1?
1K
0J
0I
1H
#13500
0&
b11011010 X
0+
0=
1<
19
08
17
0N
b1 2
b1100 ,
0T
0S
0R
0Q
#14000
1&
1+
1N
b0 Z
b0 Y
b0 [
b11111111 ]
b0 \
b0 ^
b100000 [
b1 ^
b100010011 [
b10 ^
b101010001 [
b11 ^
b1000110110 [
b100 ^
b1000111001 [
b101 ^
b1001000101 [
b110 ^
b1010111001 [
b111 ^
b1100110010 [
b1000 ^
b1011011 Z
b0 ^
b111011 \
b100000 Y
b111011 ]
b1 ^
b10 ^
b11101 \
b111110 Y
b11101 ]
b11 ^
b100 ^
b1011000 \
b101 ^
b1001111 \
b110 ^
b111 ^
b1000 ^
b1011010 \
b1001 ^
b11011010 3
b11 /
0E
1D
1@
0?
1L
0K
1J
1I
0H
#14500
0&
b10101100 X
0+
0<
1;
09
18
07
0N
b110000 2
b1101 ,
0W
1S
1R
#15000
1&
1+
1N
b0 Z
b0 Y
b0 [
b11111111 ]
b0 \
b0 ^
b11110011 [
b1 ^
b100110001 [
b10 ^
b1000010110 [
b11 ^
b1000011001 [
b100 ^
b1000100101 [
b101 ^
b1010011001 [
b110 ^
b1100010010 [
b111 ^
b1100010011 [
b1000 ^
b1011100 Z
b0 ^
b1 ^
b11110 \
b111110 Y
b11110 ]
b10 ^
b11 ^
b1011001 \
b100 ^
b1010000 \
b101 ^
b110 ^
b111 ^
b1011011 \
b1000 ^
b101100 \
b1001 ^
b10101100 3
b100 /
0M
0L
1K
#15500
0&
b10101110 X
0+
1<
0N
b101110 2
b1110 ,
1V
1U
1T
0S
#16000
1&
1+
1N
b0 Z
b0 Y
b0 [
b11111111 ]
b0 \
b0 ^
b111110 [
b1 ^
b100100011 [
b10 ^
b100100110 [
b11 ^
b100110010 [
b100 ^
b110100110 [
b101 ^
b1000011111 [
b110 ^
b1000100000 [
b111 ^
b1001010000 [
b1000 ^
b1000110 Z
b0 ^
b1000 \
b111110 Y
b1000 ]
b1 ^
b10 ^
b1000011 \
b11 ^
b111010 \
b100 ^
b101 ^
b110 ^
b1000101 \
b111 ^
b10110 \
b1000 ^
b11000 \
b1001 ^
b10101110 3
b101 /
1L
0J
0I
#16500
0&
b10010101 X
0+
1=
0<
0:
19
08
0N
b10100100 2
b1111 ,
0V
0T
1P
#17000
1&
1+
1N
b0 Z
b0 Y
b0 [
b11111111 ]
b0 \
b0 ^
b11100101 [
b1 ^
b11101000 [
b10 ^
b11110100 [
b11 ^
b101101000 [
b100 ^
b111100001 [
b101 ^
b111100010 [
b110 ^
b1000010010 [
b111 ^
b1001000000 [
b1000 ^
b1010010 Z
b0 ^
b1 ^
b1001111 \
b11 Y
b1001111 ]
b10 ^
b1000110 \
b1100 Y
b1000110 ]
b11 ^
b100 ^
b101 ^
b1010001 \
b110 ^
b100010 \
b110000 Y
b100010 ]
b111 ^
b100100 \
b1000 ^
b1001 ^
b10010101 3
b110 /
0D
0C
0B
0K
1I
#17500
0&
b10010010 X
0+
0=
1<
0;
0N
b1110110 2
b10000 ,
1V
1S
1Q
0P
#18000
1&
1+
1N
b0 Z
b0 Y
b0 [
b11111111 ]
b0 \
b0 ^
b11 [
b1 ^
b1111 [
b10 ^
b10000011 [
b11 ^
b11111100 [
b100 ^
b11111101 [
b101 ^
b100101101 [
b110 ^
b101011011 [
b111 ^
b111111111 [
b1000 ^
b1000101 Z
b0 ^
b1000010 \
b11 Y
b1000010 ]
b1 ^
b111001 \
b1100 Y
b111001 ]
b10 ^
b11 ^
b100 ^
b1000100 \
b101 ^
b10101 \
b110000 Y
b10101 ]
b110 ^
b10111 \
b111 ^
b1000 ^
b1001 ^
b10010010 3
b111 /
1M
0L
1K
0I
#18500
0&
b10000100 X
0+
0<
1;
09
0N
b10000100 2
b10001 ,
0V
0S
0R
0Q
1P
#19000
1&
1+
1N
b0 Z
b0 Y
b0 [
b11111111 ]
b0 \
b0 ^
b1100 [
b1 ^
b10000000 [
b10 ^
b11111001 [
b11 ^
b11111010 [
b100 ^
b100101010 [
b101 ^
b101011000 [
b110 ^
b111111100 [
b111 ^
b1001110010 [
b1000 ^
b1010100 Z
b0 ^
b1001000 \
b1100 Y
b1001000 ]
b1 ^
b10 ^
b11 ^
b1010011 \
b100 ^
b100100 \
b110000 Y
b100100 ]
b101 ^
b100110 \
b110 ^
b111 ^
b1000 ^
b1001 ^
b10000100 3
b1000 /
0M
1I
#19500
0&
b10010100 X
0+
19
0N
b1010001 2
b10010 ,
1W
0U
1S
1Q
0P
#20000
1&
1+
1N
b0 Z
b0 Y
b0 [
b11111111 ]
b0 \
b0 ^
b1110100 [
b1 ^
b11101101 [
b10 ^
b11101110 [
b11 ^
b100011110 [
b100 ^
b101001100 [
b101 ^
b111110000 [
b110 ^
b1001100110 [
b111 ^
b1011101010 [
b1000 ^
b1011011 Z
b0 ^
b1 ^
b10 ^
b1011010 \
b1 Y
b1011010 ]
b11 ^
b101011 \
b110000 Y
b101011 ]
b100 ^
b101101 \
b101 ^
b110 ^
b111 ^
b1000 ^
b1010 \
b1010001 Y
b1010 ]
b1001 ^
b10010100 3
b1001 /
1E
0@
1?
1M
1L
0K
1J
#20500
0&
b11000010 X
0+
1<
0;
09
17
0N
b11010110 2
b10011 ,
0W
1V
1U
1P
#21000
1&
1+
1N
b0 Z
b0 Y
b0 [
b11111111 ]
b0 \
b0 ^
b1111001 [
b1 ^
b1111010 [
b10 ^
b10101010 [
b11 ^
b11011000 [
b100 ^
b101111100 [
b101 ^
b111110010 [
b110 ^
b1001110110 [
b111 ^
b1011000111 [
b1000 ^
b1100110 Z
b0 ^
b1 ^
b1100101 \
b1 Y
b1100101 ]
b10 ^
b110110 \
b110000 Y
b110110 ]
b11 ^
b111000 \
b100 ^
b101 ^
b110 ^
b111 ^
b10101 \
b1010001 Y
b10101 ]
b1000 ^
b1001 ^
b11000010 3
b1010 /
0M
1K
0J
0I
1H
#21500
0&
b11001110 X
0+
1;
1:
0N
b1110000 2
b10100 ,
0V
0U
1R
0P
#22000
1&
1+
1N
b0 Z
b0 Y
b0 [
b11111111 ]
b0 \
b0 ^
b1 [
b1 ^
b110001 [
b10 ^
b1011111 [
b11 ^
b100000011 [
b100 ^
b101111001 [
b101 ^
b111111101 [
b110 ^
b1001001110 [
b111 ^
b1100100100 [
b1000 ^
b1100101 Z
b0 ^
b1100100 \
b1 Y
b1100100 ]
b1 ^
b110101 \
b110000 Y
b110101 ]
b10 ^
b110111 \
b11 ^
b100 ^
b101 ^
b110 ^
b10100 \
b1010001 Y
b10100 ]
b111 ^
b1000 ^
b1001 ^
b11001110 3
b1011 /
1M
0L
#22500
0&
b11001101 X
0+
1=
0<
0N
b110101 2
b10101 ,
1W
1U
0Q
#23000
1&
1+
1N
b0 Z
b0 Y
b0 [
b11111111 ]
b0 \
b0 ^
b110000 [
b1 ^
b1011110 [
b10 ^
b100000010 [
b11 ^
b101111000 [
b100 ^
b111111100 [
b101 ^
b1001001101 [
b110 ^
b1100100011 [
b111 ^
b1110010011 [
b1000 ^
b1101011 Z
b0 ^
b111011 \
b110000 Y
b111011 ]
b1 ^
b111101 \
b10 ^
b11 ^
b100 ^
b101 ^
b11010 \
b1010001 Y
b11010 ]
b110 ^
b111 ^
b1000 ^
b110110 \
b1001 ^
b11001101 3
b1100 /
1L
0K
1J
#23500
0&
b11010100 X
0+
0=
0:
19
0N
b10000 2
b10110 ,
0W
0U
0R
#24000
1&
1+
1N
b0 Z
b0 Y
b0 [
b11111111 ]
b0 \
b0 ^
b101110 [
b1 ^
b11010010 [
b10 ^
b101001000 [
b11 ^
b111001100 [
b100 ^
b1000011101 [
b101 ^
b1011110011 [
b110 ^
b1101100011 [
b111 ^
b1110011000 [
b1000 ^
b1101000 Z
b0 ^
b111010 \
b101110 Y
b111010 ]
b1 ^
b10 ^
b11 ^
b100 ^
b10111 \
b1010001 Y
b10111 ]
b101 ^
b110 ^
b111 ^
b110011 \
b1000 ^
b1011000 \
b1001 ^
b11010100 3
b1101 /
0M
0L
#24500
0&
b11010000 X
0+
0;
0N
b100011 2
b10111 ,
1W
1V
0S
1R
#25000
1&
1+
1N
b0 Z
b0 Y
b0 [
b11111111 ]
b0 \
b0 ^
b10100100 [
b1 ^
b100011010 [
b10 ^
b110011110 [
b11 ^
b111101111 [
b100 ^
b1011000101 [
b101 ^
b1100110101 [
b110 ^
b1101101010 [
b111 ^
b1101111010 [
b1000 ^
b1100110 Z
b0 ^
b1 ^
b10 ^
b11 ^
b10101 \
b1010001 Y
b10101 ]
b100 ^
b101 ^
b110 ^
b110001 \
b111 ^
b1010110 \
b1000 ^
b1000011 \
b1001 ^
b11010000 3
b1110 /
1L
1K
0J
#25500
0&
b11001110 X
0+
1<
1;
1:
09
0N
b11100111 2
b11000 ,
1U
1Q
1P
#26000
1&
1+
1N
b0 Z
b0 Y
b0 [
b11111111 ]
b0 \
b0 ^
b1110110 [
b1 ^
b11111010 [
b10 ^
b101001011 [
b11 ^
b1000100001 [
b100 ^
b1010010001 [
b101 ^
b1011000110 [
b110 ^
b1011010110 [
b111 ^
b1011111001 [
b1000 ^
b1101110 Z
b0 ^
b1 ^
b10 ^
b11101 \
b1010001 Y
b11101 ]
b11 ^
b100 ^
b101 ^
b111001 \
b110 ^
b1011110 \
b111 ^
b1001011 \
b1000 ^
b1001 ^
b11001110 3
b1111 /
1J
#26500
0&
b11010111 X
0+
1=
0:
19
0N
b111011 2
b11001 ,
0U
1T
1S
0Q
0P
#27000
1&
1+
1N
b0 Z
b0 Y
b0 [
b11111111 ]
b0 \
b0 ^
b10000100 [
b1 ^
b11010101 [
b10 ^
b110101011 [
b11 ^
b1000011011 [
b100 ^
b1001010000 [
b101 ^
b1001100000 [
b110 ^
b1010000011 [
b111 ^
b1101101010 [
b1000 ^
b1100111 Z
b0 ^
b1 ^
b10110 \
b1010001 Y
b10110 ]
b10 ^
b11 ^
b100 ^
b110010 \
b101 ^
b1010111 \
b110 ^
b1000100 \
b111 ^
b1000 ^
b101100 \
b1001 ^
b11010111 3
b10000 /
1M
0J
#27500
0&
b11001111 X
0+
1:
09
0N
b1101101 2
b11010 ,
0V
1U
0S
1Q
#28000
1&
1+
1N
b0 Z
b0 Y
b0 [
b11111111 ]
b0 \
b0 ^
b1010001 [
b1 ^
b100100111 [
b10 ^
b110010111 [
b11 ^
b111001100 [
b100 ^
b111011100 [
b101 ^
b111111111 [
b110 ^
b1011100110 [
b111 ^
b1100100001 [
b1000 ^
b1100101 Z
b0 ^
b10100 \
b1010001 Y
b10100 ]
b1 ^
b10 ^
b11 ^
b110000 \
b100 ^
b1010101 \
b101 ^
b1000010 \
b110 ^
b111 ^
b101010 \
b1000 ^
b1001 ^
b11001111 3
b10001 /
0L
#28500
0&
b11001100 X
0+
0=
0<
0N
b110100 2
b11011 ,
0W
0T
1S
0Q
#29000
1&
1+
1N
b0 Z
b0 Y
b0 [
b11111111 ]
b0 \
b0 ^
b11010110 [
b1 ^
b101000110 [
b10 ^
b101111011 [
b11 ^
b110001011 [
b100 ^
b110101110 [
b101 ^
b1010010101 [
b110 ^
b1011010000 [
b111 ^
b1100111101 [
b1000 ^
b1100001 Z
b0 ^
b1 ^
b10 ^
b101100 \
b110101 Y
b101100 ]
b11 ^
b1010001 \
b100 ^
b111110 \
b101 ^
b110 ^
b100110 \
b111011 Y
b100110 ]
b111 ^
b1000 ^
b101101 \
b1001 ^
b11001100 3
b10010 /
1D
1B
1@
0?
0K
#29500
0&
b10110000 X
0+
0;
0:
19
18
07
0N
b1100001 2
b11100 ,
1W
0U
0S
1Q
#30000
1&
1+
1N
b0 Z
b0 Y
b0 [
b11111111 ]
b0 \
b0 ^
b1110000 [
b1 ^
b10100101 [
b10 ^
b10110101 [
b11 ^
b11011000 [
b100 ^
b110111111 [
b101 ^
b111111010 [
b110 ^
b1001100111 [
b111 ^
b1010011011 [
b1000 ^
b1010100 Z
b0 ^
b1 ^
b11111 \
b110101 Y
b11111 ]
b10 ^
b1000100 \
b11 ^
b110001 \
b100 ^
b101 ^
b11001 \
b111011 Y
b11001 ]
b110 ^
b111 ^
b100000 \
b1000 ^
b1001 ^
b10110000 3
b10011 /
0M
1K
1I
0H
#30500
0&
b10100001 X
0+
1=
09
0N
b10001001 2
b11101 ,
1T
0R
0Q
1P
#31000
1&
1+
1N
b0 Z
b0 Y
b0 [
b11111111 ]
b0 \
b0 ^
b110101 [
b1 ^
b1000101 [
b10 ^
b1101000 [
b11 ^
b101001111 [
b100 ^
b110001010 [
b101 ^
b111110111 [
b110 ^
b1000101011 [
b111 ^
b1010001100 [
b1000 ^
b1010111 Z
b0 ^
b100010 \
b110101 Y
b100010 ]
b1 ^
b1000111 \
b10 ^
b110100 \
b11 ^
b100 ^
b11100 \
b111011 Y
b11100 ]
b101 ^
b110 ^
b100011 \
b111 ^
b1000 ^
b1001 ^
b10100001 3
b10100 /
1M
1L
#31500
0&
b10100101 X
0+
1;
0N
b10111111 2
b11110 ,
1V
1U
1S
1R
#32000
1&
1+
1N
b0 Z
b0 Y
b0 [
b11111111 ]
b0 \
b0 ^
b10000 [
b1 ^
b110011 [
b10 ^
b100011010 [
b11 ^
b101010101 [
b100 ^
b111000010 [
b101 ^
b111110110 [
b110 ^
b1001010111 [
b111 ^
b1011100000 [
b1000 ^
b1100111 Z
b0 ^
b1010111 \
b10000 Y
b1010111 ]
b1 ^
b1000100 \
b100011 Y
b1000100 ]
b10 ^
b11 ^
b101100 \
b111011 Y
b101100 ]
b100 ^
b101 ^
b110011 \
b110 ^
b110 \
b1100001 Y
b110 ]
b111 ^
b1000 ^
b1001 ^
b10100101 3
b10101 /
0D
0B
0A
1?
0I
1H
#32500
0&
b11100001 X
0+
0;
17
0N
b11011100 2
b11111 ,
0W
0V
0R
1Q
#33000
1&
1+
1N
b0 Z
b0 Y
b0 [
b11111111 ]
b0 \
b0 ^
b100011 [
b1 ^
b100001010 [
b10 ^
b101000101 [
b11 ^
b110110010 [
b100 ^
b111100110 [
b101 ^
b1001000111 [
b110 ^
b1011010000 [
b111 ^
b1110001111 [
b1000 ^
b1111101 Z
b0 ^
b1011010 \
b100011 Y
b1011010 ]
b1 ^
b10 ^
b1000010 \
b111011 Y
b1000010 ]
b11 ^
b10000 \
b1101101 Y
b10000 ]
b100 ^
b1001001 \
b101 ^
b11100 \
b110 ^
b111 ^
b1000 ^
b1001 ^
b11100001 3
b10110 /
1C
1B
0L
1J
1I
#33500
0&
b100001000 X
0+
0=
1:
08
07
06
15
0N
b11010011 2
b100000 ,
1W
1V
0U
0T
#34000
1&
1+
1N
b0 Z
b0 Y
b0 [
b11111111 ]
b0 \
b0 ^
b11100111 [
b1 ^
b100100010 [
b10 ^
b110001111 [
b11 ^
b111000011 [
b100 ^
b1000100100 [
b101 ^
b1010101101 [
b110 ^
b1101101100 [
b111 ^
b10001001000 [
b1000 ^
b10010001 Z
b0 ^
b1 ^
b1010110 \
b111011 Y
b1010110 ]
b10 ^
b100100 \
b1101101 Y
b100100 ]
b11 ^
b1011101 \
b100 ^
b110000 \
b101 ^
b1000 \
b10001001 Y
b1000 ]
b110 ^
b111 ^
b1000 ^
b1001 ^
b100001000 3
b10111 /
0C
0@
0?
1>
0K
0J
0H
0G
1F
#34500
0&
b100111101 X
0+
1=
1;
19
18
0N
b10011100 2
b100001 ,
0W
0V
1U
1T
0Q
